sklearn_pandas/__init__.py
sklearn_pandas/cross_validation.py
sklearn_pandas/dataframe_mapper.py
sklearn_pandas/features_generator.py
sklearn_pandas/pipeline.py
sklearn_pandas/transformers.py
sklearn_pandas-2.0.4.dist-info/LICENSE
sklearn_pandas-2.0.4.dist-info/METADATA
sklearn_pandas-2.0.4.dist-info/WHEEL
sklearn_pandas-2.0.4.dist-info/top_level.txt
sklearn_pandas-2.0.4.dist-info/RECORD
