Metadata-Version: 2.1
Name: sklearn-pandas
Version: 2.0.4
Summary: Pandas integration with sklearn
Home-page: https://github.com/scikit-learn-contrib/sklearn-pandas
Maintainer: Ritesh Agrawal
Maintainer-email: ragrawal@gmail.com
License: UNKNOWN
Keywords: scikit,sklearn,pandas
Platform: UNKNOWN
Requires-Dist: scikit-learn (>=0.23.0)
Requires-Dist: scipy (>=1.4.1)
Requires-Dist: pandas (>=1.0.5)
Requires-Dist: numpy (>=1.18.1)
